witskit/__init__.py
witskit/cli.py
witskit/decoder/__init__.py
witskit/decoder/wits_decoder.py
witskit/models/__init__.py
witskit/models/symbols.py
witskit/models/unit_converter.py
witskit/models/wits_frame.py
witskit/storage/__init__.py
witskit/storage/base.py
witskit/storage/schema.py
witskit/storage/sql_writer.py
witskit/transport/__init__.py
witskit/transport/base.py
witskit/transport/file_reader.py
witskit/transport/pason_serial_reader.py
witskit/transport/pason_tcp_reader.py
witskit/transport/requesting_tcp_reader.py
witskit/transport/serial_reader.py
witskit/transport/tcp_reader.py
witskit-0.1.0.dist-info/METADATA
witskit-0.1.0.dist-info/WHEEL
witskit-0.1.0.dist-info/entry_points.txt
witskit-0.1.0.dist-info/licenses/LICENSE
witskit-0.1.0.dist-info/RECORD
