Metadata-Version: 2.4
Name: witskit
Version: 0.1.0
Summary: The most comprehensive Python SDK for processing WITS (Wellsite Information Transfer Standard) data in the oil & gas drilling industry.
Project-URL: Homepage, https://github.com/Critlist/witskit
Project-URL: Documentation, https://github.com/Critlist/witskit#readme
Project-URL: Repository, https://github.com/Critlist/witskit
Project-URL: Issues, https://github.com/Critlist/witskit/issues
Author-email: Mikey Howk <howktechllc@gmail.com>
License-Expression: MIT
License-File: LICENSE
Keywords: drilling,logging,lwd,mwd,oil-gas,wits
Classifier: Development Status :: 4 - Beta
Classifier: Intended Audience :: Developers
Classifier: Intended Audience :: Science/Research
Classifier: License :: OSI Approved :: MIT License
Classifier: Operating System :: OS Independent
Classifier: Programming Language :: Python :: 3
Classifier: Programming Language :: Python :: 3.11
Classifier: Programming Language :: Python :: 3.12
Classifier: Programming Language :: Python :: 3.13
Classifier: Topic :: Scientific/Engineering
Classifier: Topic :: Software Development :: Libraries :: Python Modules
Requires-Python: >=3.11
Requires-Dist: loguru>=0.7.3
Requires-Dist: pydantic>=2.11.5
Requires-Dist: pyserial>=3.5
Requires-Dist: rich>=14.0.0
Requires-Dist: sqlalchemy>=2.0.41
Requires-Dist: tqdm>=4.67.1
Requires-Dist: typer>=0.16.0
Provides-Extra: dev
Requires-Dist: black>=23.0.0; extra == 'dev'
Requires-Dist: mypy>=1.5.0; extra == 'dev'
Requires-Dist: pytest-cov>=4.0.0; extra == 'dev'
Requires-Dist: pytest>=8.4.0; extra == 'dev'
Requires-Dist: ruff>=0.1.0; extra == 'dev'
Provides-Extra: docs
Requires-Dist: mkdocs-autorefs>=0.5.0; extra == 'docs'
Requires-Dist: mkdocs-material-extensions>=1.3.0; extra == 'docs'
Requires-Dist: mkdocs-material>=9.5.0; extra == 'docs'
Requires-Dist: mkdocs>=1.5.0; extra == 'docs'
Requires-Dist: mkdocstrings[python]>=0.24.0; extra == 'docs'
Provides-Extra: mysql
Requires-Dist: aiomysql>=0.2.0; extra == 'mysql'
Requires-Dist: pymysql>=1.1.0; extra == 'mysql'
Requires-Dist: sqlalchemy>=2.0.0; extra == 'mysql'
Provides-Extra: postgres
Requires-Dist: asyncpg>=0.29.0; extra == 'postgres'
Requires-Dist: psycopg2-binary>=2.9.0; extra == 'postgres'
Requires-Dist: sqlalchemy>=2.0.0; extra == 'postgres'
Provides-Extra: sql
Requires-Dist: aiosqlite>=0.19.0; extra == 'sql'
Requires-Dist: sqlalchemy>=2.0.0; extra == 'sql'
Provides-Extra: test
Requires-Dist: pytest-cov>=4.1.0; extra == 'test'
Requires-Dist: pytest>=8.4.0; extra == 'test'
